onnxmltools/__init__.py
onnxmltools/convert/__init__.py
onnxmltools/convert/main.py
onnxmltools/convert/common/__init__.py
onnxmltools/convert/common/_apply_operation.py
onnxmltools/convert/common/_container.py
onnxmltools/convert/common/_registration.py
onnxmltools/convert/common/_topology.py
onnxmltools/convert/common/case_insensitive_dict.py
onnxmltools/convert/common/data_types.py
onnxmltools/convert/common/interface.py
onnxmltools/convert/common/onnx_ex.py
onnxmltools/convert/common/shape_calculator.py
onnxmltools/convert/common/tree_ensemble.py
onnxmltools/convert/common/utils.py
onnxmltools/convert/coreml/__init__.py
onnxmltools/convert/coreml/_parse.py
onnxmltools/convert/coreml/convert.py
onnxmltools/convert/coreml/operator_converters/ArrayFeatureExtractor.py
onnxmltools/convert/coreml/operator_converters/DictVectorizer.py
onnxmltools/convert/coreml/operator_converters/FeatureVectorizer.py
onnxmltools/convert/coreml/operator_converters/GLMClassifier.py
onnxmltools/convert/coreml/operator_converters/GLMRegressor.py
onnxmltools/convert/coreml/operator_converters/Identity.py
onnxmltools/convert/coreml/operator_converters/Imputer.py
onnxmltools/convert/coreml/operator_converters/Normalizer.py
onnxmltools/convert/coreml/operator_converters/OneHotEncoder.py
onnxmltools/convert/coreml/operator_converters/SVC.py
onnxmltools/convert/coreml/operator_converters/SVR.py
onnxmltools/convert/coreml/operator_converters/Scaler.py
onnxmltools/convert/coreml/operator_converters/TensorToLabel.py
onnxmltools/convert/coreml/operator_converters/TensorToProbabilityMap.py
onnxmltools/convert/coreml/operator_converters/TreeEnsemble.py
onnxmltools/convert/coreml/operator_converters/__init__.py
onnxmltools/convert/coreml/operator_converters/neural_network/Activation.py
onnxmltools/convert/coreml/operator_converters/neural_network/Add.py
onnxmltools/convert/coreml/operator_converters/neural_network/Average.py
onnxmltools/convert/coreml/operator_converters/neural_network/BatchNorm.py
onnxmltools-1.13.0.dist-info/LICENSE
onnxmltools-1.13.0.dist-info/METADATA
onnxmltools-1.13.0.dist-info/WHEEL
onnxmltools-1.13.0.dist-info/top_level.txt
onnxmltools-1.13.0.dist-info/RECORD
