Metadata-Version: 2.1
Name: onnxmltools
Version: 1.13.0
Summary: Converts Machine Learning models to ONNX
Home-page: https://github.com/onnx/onnxmltools
Author: ONNX
Author-email: onnx-technical-discuss@lists.lfaidata.foundation
License: Apache License v2.0
Classifier: Development Status :: 4 - Beta
Classifier: Environment :: Console
Classifier: Intended Audience :: Developers
Classifier: Operating System :: MacOS :: MacOS X
Classifier: Operating System :: Microsoft :: Windows
Classifier: Programming Language :: Python
Classifier: Programming Language :: Python :: 3.5
Classifier: Programming Language :: Python :: 3.6
Classifier: Programming Language :: Python :: 3.7
Classifier: License :: OSI Approved :: Apache Software License
License-File: LICENSE
Requires-Dist: numpy
Requires-Dist: onnx
Requires-Dist: onnxconverter-common
